thaiqr_gaming-0.3.0.dist-info/licenses/LICENSE
thaiqrpayment/__init__.py
thaiqrpayment/assets/logo.png
thaiqrpayment/assets/template.png
thaiqr_gaming-0.3.0.dist-info/METADATA
thaiqr_gaming-0.3.0.dist-info/WHEEL
thaiqr_gaming-0.3.0.dist-info/top_level.txt
thaiqr_gaming-0.3.0.dist-info/RECORD
