Metadata-Version: 2.4
Name: thaiqr-gaming
Version: 0.3.0
Summary: Thai QR Payment Generator with Gaming Features and Anti-Fraud Security
Home-page: https://github.com/kittinan/thai-qr-payment
Author: Kittinan Srithaworn
License: MIT
Project-URL: Bug Reports, https://github.com/kittinan/thai-qr-payment/issues
Project-URL: Source, https://github.com/kittinan/thai-qr-payment
Keywords: Thai QR Payment Generator Gaming Anti-Fraud Security Watermark
Classifier: Programming Language :: Python :: 3
Classifier: License :: OSI Approved :: MIT License
Classifier: Operating System :: OS Independent
Requires-Python: >=3.6
License-File: LICENSE
Requires-Dist: qrcode
Requires-Dist: pillow
Requires-Dist: crc16
Dynamic: author
Dynamic: classifier
Dynamic: description
Dynamic: description-content-type
Dynamic: home-page
Dynamic: keywords
Dynamic: license
Dynamic: license-file
Dynamic: project-url
Dynamic: requires-dist
Dynamic: requires-python
Dynamic: summary
